gbasis/__init__.py
gbasis/base.py
gbasis/base_four_symm.py
gbasis/base_one.py
gbasis/base_two_asymm.py
gbasis/base_two_symm.py
gbasis/contractions.py
gbasis/parsers.py
gbasis/spherical.py
gbasis/utils.py
gbasis/wrappers.py
gbasis/evals/__init__.py
gbasis/evals/_deriv.py
gbasis/evals/density.py
gbasis/evals/electrostatic_potential.py
gbasis/evals/eval.py
gbasis/evals/eval_deriv.py
gbasis/evals/stress_tensor.py
gbasis/integrals/__init__.py
gbasis/integrals/_diff_operator_int.py
gbasis/integrals/_moment_int.py
gbasis/integrals/_one_elec_int.py
gbasis/integrals/_two_elec_int.py
gbasis/integrals/angular_momentum.py
gbasis/integrals/electron_repulsion.py
gbasis/integrals/kinetic_energy.py
gbasis/integrals/libcint.py
gbasis/integrals/moment.py
gbasis/integrals/momentum.py
gbasis/integrals/nuclear_electron_attraction.py
gbasis/integrals/overlap.py
gbasis/integrals/overlap_asymm.py
gbasis/integrals/point_charge.py
qc_gbasis-0.1.0.dist-info/LICENSE
qc_gbasis-0.1.0.dist-info/METADATA
qc_gbasis-0.1.0.dist-info/WHEEL
qc_gbasis-0.1.0.dist-info/top_level.txt
qc_gbasis-0.1.0.dist-info/RECORD
