Metadata-Version: 2.1
Name: qc-gbasis
Version: 0.1.0
Summary: A module for evaluating, differentiating, and integrating Gaussian functions.
Author-email: QC-Devs Community <qcdevs@gmail.com>
License: GPL-3.0-or-later
Project-URL: Documentation, https://gbasis.qcdevs.org
Project-URL: Issues, https://github.com/theochem/gbasis/issues
Project-URL: Source, https://github.com/theochem/gbasis/
Project-URL: Changelog, https://github.com/theochem/gbasis/blob/main/CHANGELOG.md
Project-URL: Organization, https://github.com/theochem/
Classifier: Development Status :: 5 - Production/Stable
Classifier: Environment :: Console
Classifier: License :: OSI Approved :: GNU General Public License v3 or later (GPLv3+)
Classifier: Operating System :: POSIX :: Linux
Classifier: Operating System :: MacOS
Classifier: Operating System :: Microsoft :: Windows
Classifier: Topic :: Scientific/Engineering :: Physics
Classifier: Topic :: Scientific/Engineering :: Chemistry
Classifier: Topic :: Scientific/Engineering :: Mathematics
Classifier: Intended Audience :: Science/Research
Classifier: Intended Audience :: Education
Classifier: Intended Audience :: Developers
Classifier: Natural Language :: English
Classifier: Programming Language :: Python :: 3.9
Classifier: Programming Language :: Python :: 3.10
Classifier: Programming Language :: Python :: 3.11
Classifier: Programming Language :: Python :: 3.12
Requires-Python: >=3.9
License-File: LICENSE
Requires-Dist: scipy >=1.11.1
Requires-Dist: importlib-resources
Requires-Dist: sympy
Requires-Dist: numpy >=1.22 ; platform_system == "Linux"
Requires-Dist: numpy <2.0.0,>=1.22 ; platform_system == "Windows"
Provides-Extra: dev
Requires-Dist: tox ; extra == 'dev'
Requires-Dist: pre-commit ; extra == 'dev'
Requires-Dist: pytest ; extra == 'dev'
Requires-Dist: pytest-cov ; extra == 'dev'
Requires-Dist: pytest-timeout ; extra == 'dev'
Requires-Dist: pytest-xdist ; extra == 'dev'
Requires-Dist: pytest-md ; extra == 'dev'
Requires-Dist: setuptools-scm ; extra == 'dev'
Requires-Dist: sphinx ; extra == 'dev'
Requires-Dist: sphinx-autodoc-typehints ; extra == 'dev'
Requires-Dist: sphinx-copybutton ; extra == 'dev'
Provides-Extra: doc
Requires-Dist: numpydoc ; extra == 'doc'
Requires-Dist: sphinx-copybutton ; extra == 'doc'
Requires-Dist: sphinx-autoapi ; extra == 'doc'
Requires-Dist: nbsphinx ; extra == 'doc'
Requires-Dist: sphinx-rtd-theme ; extra == 'doc'
Requires-Dist: sphinx-autodoc-typehints ; extra == 'doc'
Requires-Dist: docutils ==0.16 ; extra == 'doc'
Requires-Dist: nbsphinx-link ; extra == 'doc'
Provides-Extra: iodata
Requires-Dist: qc-iodata >=1.0.0a5 ; extra == 'iodata'
Provides-Extra: pyscf
Requires-Dist: pyscf >=1.6.1 ; extra == 'pyscf'
